mojito/__init__.py
mojito/koreainvestment.py
mojito/base/__init__.py
mojito/base/broker.py
mojito2-0.1.6.dist-info/LICENSE
mojito2-0.1.6.dist-info/METADATA
mojito2-0.1.6.dist-info/WHEEL
mojito2-0.1.6.dist-info/top_level.txt
mojito2-0.1.6.dist-info/RECORD
