Metadata-Version: 2.1
Name: mojito2
Version: 0.1.6
Summary: python wrapper for korea broker's REST API services
Home-page: https://github.com/sharebook-kr/mojito
Author: Jonghun Yoo, Brayden Jo
Author-email: jonghun.yoo@pyquant.co.kr, brayden.jo@pyquant.co.kr
Classifier: Programming Language :: Python :: 3
Classifier: License :: OSI Approved :: Apache Software License
Classifier: Operating System :: OS Independent
Requires-Python: >=3.6
License-File: LICENSE
